groupticketfields/__init__.py
groupticketfields/ticket.py
groupticketfields/htdocs/collapsed.png
groupticketfields/htdocs/expanded.png
groupticketfields/htdocs/group_ticket_fields.js
groupticketfields/htdocs/css/ticket.css
TracGroupTicketFields-0.3.dist-info/COPYING
TracGroupTicketFields-0.3.dist-info/METADATA
TracGroupTicketFields-0.3.dist-info/WHEEL
TracGroupTicketFields-0.3.dist-info/entry_points.txt
TracGroupTicketFields-0.3.dist-info/top_level.txt
TracGroupTicketFields-0.3.dist-info/RECORD
