Metadata-Version: 2.1
Name: TracGroupTicketFields
Version: 0.3
Summary: Group Ticket Fields
Home-page: https://trac-hacks.org/wiki/GroupTicketFieldsPlugin
Author: thomasd
Author-email: tdoering@baumer.com
License: BSD 3-Clause
Keywords: Group Ticket Fields
Platform: UNKNOWN
Classifier: Framework :: Trac
